README.md
setup.py
tmscoring/__init__.py
tmscoring/tmscore.py
tmscoring.egg-info/PKG-INFO
tmscoring.egg-info/SOURCES.txt
tmscoring.egg-info/dependency_links.txt
tmscoring.egg-info/pbr.json
tmscoring.egg-info/top_level.txt